jsonlitedb.py
jsonlitedb-0.1.11.dist-info/METADATA
jsonlitedb-0.1.11.dist-info/WHEEL
jsonlitedb-0.1.11.dist-info/entry_points.txt
jsonlitedb-0.1.11.dist-info/top_level.txt
jsonlitedb-0.1.11.dist-info/RECORD
