Metadata-Version: 2.4
Name: jsonlitedb
Version: 0.1.11
Summary: SQLite3-backed JSON document database with support for indices and advanced queries
Author-email: Justin Winokur <Jwink3101@users.noreply.github.com>
License: Copyright 2026 Justin Winokur
Project-URL: Homepage, https://github.com/Jwink3101/jsonlitedb
Project-URL: Source, https://github.com/Jwink3101/jsonlitedb
Project-URL: Issues, https://github.com/Jwink3101/jsonlitedb/issues
Classifier: Programming Language :: Python :: 3
Classifier: License :: OSI Approved :: MIT License
Classifier: Operating System :: OS Independent
Requires-Python: >=3.8
